MANIFEST.in
README.rst
bottle_msgpack.py
requirements.txt
setup.py
bottle_msgpack.egg-info/PKG-INFO
bottle_msgpack.egg-info/SOURCES.txt
bottle_msgpack.egg-info/dependency_links.txt
bottle_msgpack.egg-info/requires.txt
bottle_msgpack.egg-info/top_level.txt