Metadata-Version: 1.1
Name: bottle-msgpack
Version: 0.0.2
Summary: MsgPack integration for Bottle.
Home-page: https://github.com/nachopro/bottle-msgpack
Author: Ignacio Juan Martín Benedetti
Author-email: tranceway@gmail.com
License: MIT
Platform: any
Classifier: Environment :: Web Environment
Classifier: Intended Audience :: Developers
Classifier: License :: OSI Approved :: MIT License
Classifier: Operating System :: OS Independent
Classifier: Programming Language :: Python
Classifier: Topic :: Internet :: WWW/HTTP :: Dynamic Content
Classifier: Topic :: Software Development :: Libraries :: Python Modules
Classifier: Framework :: Bottle
